peft_ex/__init__.py
peft_ex/optim/__init__.py
peft_ex/optim/common.py
peft_ex/optim/functional.py
peft_ex/optim/lora.py
peft_ex/optim/lora_plus.py
peft_ex/optim/spectune.py
peft_ex/wrapper/__init__.py
peft_ex/wrapper/common.py
peft_ex/wrapper/lora_ex.py
peft_ex/wrapper/utils.py
peft_ex-0.7.1.dist-info/LICENSE
peft_ex-0.7.1.dist-info/METADATA
peft_ex-0.7.1.dist-info/WHEEL
peft_ex-0.7.1.dist-info/top_level.txt
peft_ex-0.7.1.dist-info/zip-safe
peft_ex-0.7.1.dist-info/RECORD
