Metadata-Version: 2.1
Name: peft-ex
Version: 0.7.1
Summary: PEFT Extensions.
Author: xi
Author-email: gylv@mail.ustc.edu.cn
License: Apache License 2.0
Platform: any
Classifier: Programming Language :: Python :: 3.6
Classifier: Programming Language :: Python :: 3.7
Classifier: Programming Language :: Python :: 3.8
License-File: LICENSE
Requires-Dist: torch
Requires-Dist: libentry
